asyncpraw-stubs/__init__.pyi
asyncpraw-stubs/config.pyi
asyncpraw-stubs/const.pyi
asyncpraw-stubs/endpoints.pyi
asyncpraw-stubs/exceptions.pyi
asyncpraw-stubs/models/__init__.pyi
asyncpraw-stubs/models/auth.pyi
asyncpraw-stubs/models/base.pyi
asyncpraw-stubs/models/comment_forest.pyi
asyncpraw-stubs/models/front.pyi
asyncpraw-stubs/models/helpers.pyi
asyncpraw-stubs/models/inbox.pyi
asyncpraw-stubs/models/list.pyi
asyncpraw-stubs/models/listing/__init__.pyi
asyncpraw-stubs/models/listing/domain.py
asyncpraw-stubs/models/listing/mixins/__init__.pyi
asyncpraw-stubs/models/listing/mixins/base.pyi
asyncpraw-stubs/models/listing/mixins/rising.pyi
asyncpraw-stubs/models/listing.pyi
asyncpraw-stubs/models/mod_action.pyi
asyncpraw-stubs/models/mod_note.pyi
asyncpraw-stubs/models/mod_notes.pyi
asyncpraw-stubs/models/preferences.pyi
asyncpraw-stubs/models/reddit/__init__.pyi
asyncpraw-stubs/models/reddit/base.pyi
asyncpraw-stubs/models/reddit/collections.pyi
asyncpraw-stubs/models/reddit/comment.pyi
asyncpraw-stubs/models/reddit/draft.pyi
asyncpraw-stubs/models/reddit/emoji.pyi
asyncpraw-stubs/models/reddit/inline_media.pyi
asyncpraw-stubs/models/reddit/live.pyi
asyncpraw-stubs/models/reddit/message.pyi
asyncpraw-stubs/models/reddit/mixins/__init__.pyi
asyncpraw-stubs/models/reddit/mixins/editable.pyi
asyncpraw-stubs/models/reddit/mixins/fullname.pyi
asyncpraw-stubs/models/reddit/mixins/gildable.pyi
asyncpraw-stubs/models/reddit/mixins/inboxable.pyi
asyncpraw-stubs/models/reddit/mixins/inboxtoggleable.pyi
asyncpraw-stubs/models/reddit/mixins/messageable.pyi
asyncpraw-stubs/models/reddit/mixins/modnote.pyi
asyncpraw-stubs/models/reddit/mixins/replyable.pyi
asyncpraw-stubs/models/reddit/mixins/reportable.pyi
asyncpraw-stubs/models/reddit/mixins/savable.pyi
asyncpraw-stubs/models/reddit/mixins/votable.pyi
asyncpraw-stubs/models/reddit/modmail.pyi
asyncpraw-stubs/models/reddit/more.pyi
asyncpraw-stubs/models/reddit/multi.pyi
asyncpraw-stubs/models/reddit/poll.pyi
asyncpraw_stubs-0.0.3.dist-info/LICENSE
asyncpraw_stubs-0.0.3.dist-info/METADATA
asyncpraw_stubs-0.0.3.dist-info/WHEEL
asyncpraw_stubs-0.0.3.dist-info/RECORD
